pytest_mask_secrets-1.6.0.dist-info/METADATA
pytest_mask_secrets-1.6.0.dist-info/WHEEL
pytest_mask_secrets-1.6.0.dist-info/entry_points.txt
pytest_mask_secrets-1.6.0.dist-info/licenses/LICENSE.txt
pytest_mask_secrets/__init__.py
pytest_mask_secrets/plugin.py
pytest_mask_secrets-1.6.0.dist-info/RECORD
