Metadata-Version: 2.1
Name: pytest-mask-secrets
Version: 1.6.0
Summary: Pytest plugin to hide sensitive data in test reports
Author-Email: Marian Ganisin <23635632+mganisin@users.noreply.github.com>
License: MIT
Classifier: Programming Language :: Python :: 3
Classifier: Framework :: Pytest
Project-URL: Homepage, https://github.com/mganisin/pytest-mask-secrets
Requires-Python: >=3
